lom_api/__init__.py
lom_api/client.py
lom_api-0.1.0.dist-info/METADATA
lom_api-0.1.0.dist-info/WHEEL
lom_api-0.1.0.dist-info/top_level.txt
lom_api-0.1.0.dist-info/RECORD
